{"name":"Brian Wang","tagline":"Programmer","body":"### |[**Home**](https://brianwang9100.github.com)| |[**Projects**](https://brianwang9100.github.com/Projects)| \r\n![](https://scontent-b-atl.xx.fbcdn.net/hphotos-xfp1/t31.0-8/1094066_941506962531049_2252822425000214388_o.jpg)\r\n\r\n### ABOUT ME\r\nHi, my name is Brian Wang. I am a CS Major at Georgia Institute of Technology. I am a teacher, an Eagle Scout, and a programmer who is looking to broaden his skill-set. Nice to meet you!\r\n\r\n### SKILLS\r\nObjective-C, Java\r\n \r\nTechnologies: XCode, SpriteBuilder, Cocos2D, Google Maps API, Firebase API, Parse API, Facebook API\r\n\r\n###Projects\r\n[**Link to my projects**](https://brianwang9100.github.com/Projects)\r\n\r\n### RESUME\r\n[**Link to my resume**](https://drive.google.com/file/d/0B9mexo7XVY6sNjM0Qk9aSU1zcjg/preview)\r\n\r\n### INTERESTS\r\nMobile Development, Web Development, Video Game Development, Server Architecture, Artificial Intelligence\r\n\r\nOther Interests: Origami, Dancing, Singing, Video Games, Badminton, Community Service Projects, Teaching, Making funny faces, etc.\r\n\r\n### CONTACT INFO\r\nBrian Wang\r\n - Email: [**brianwang9100@gmail.com**](mailto:brianwang9100@gmail.com)\r\n\r\n - LinkedIn: **www.linkedin.com/in/brianwang9100**\r\n\r\n - GitHub: **www.github.com/brianwang9100**","google":"","note":"Don't delete this file! It's used internally to help with page regeneration."}